{"name":"Iniciar Sesion en la Aplicacion Web.","id":"iniciar-sesion-con-credenciales-validas.;iniciar-sesion-en-la-aplicacion-web.","scenarioId":"1inicio_seccion_HU1_Sprint2:Iniciar Sesion en la Aplicacion Web.","methodName":"Iniciar Sesion en la Aplicacion Web.","testSteps":[{"number":1,"description":"Given que estoy en la pagina de inicio de sesion Orden1","duration":798,"startTime":"2024-06-04T19:53:00.232342600-05:00[America/Bogota]","result":"SUCCESS","precondition":false,"level":0,"children":[{"number":2,"description":"Usuario open the","duration":589,"startTime":"2024-06-04T19:53:00.437733100-05:00[America/Bogota]","result":"SUCCESS","precondition":false,"level":1,"children":[{"number":3,"description":"usuario opens the Login page","duration":568,"startTime":"2024-06-04T19:53:00.455733300-05:00[America/Bogota]","result":"SUCCESS","precondition":false,"level":2}]}]},{"number":4,"description":"When ingreso mi correo electronico y contrasena","duration":971,"startTime":"2024-06-04T19:53:01.031776-05:00[America/Bogota]","result":"SUCCESS","precondition":false,"level":0,"children":[{"number":5,"description":"Usuario find out the","duration":956,"startTime":"2024-06-04T19:53:01.043777300-05:00[America/Bogota]","result":"SUCCESS","precondition":false,"level":1,"children":[{"number":6,"description":"usuario clicks on LINK INICIAR SESION HOMEPAGE","duration":118,"startTime":"2024-06-04T19:53:01.114115700-05:00[America/Bogota]","result":"SUCCESS","precondition":false,"level":2},{"number":7,"description":"usuario enters \u0027animatrix88@gmail.com\u0027 then hits [RETURN] into TITLE CORREO INICIO SESION","duration":355,"startTime":"2024-06-04T19:53:01.234515200-05:00[America/Bogota]","result":"SUCCESS","precondition":false,"level":2},{"number":8,"description":"usuario enters \u0027Torre123*\u0027 then hits [RETURN] into TITLE PASSWORD INICIO SESION","duration":155,"startTime":"2024-06-04T19:53:01.591468900-05:00[America/Bogota]","result":"SUCCESS","precondition":false,"level":2},{"number":9,"description":"usuario clicks on MARCAR TERMINOS Y CONDICIONES","duration":87,"startTime":"2024-06-04T19:53:01.747747400-05:00[America/Bogota]","result":"SUCCESS","precondition":false,"level":2},{"number":10,"description":"usuario clicks on MARCAR ACUERDO POLITICA DE PRIVACIDAD","duration":76,"startTime":"2024-06-04T19:53:01.837676200-05:00[America/Bogota]","result":"SUCCESS","precondition":false,"level":2},{"number":11,"description":"usuario clicks on LINK BOTON INICIAR SESION HOMEPAGE","duration":82,"startTime":"2024-06-04T19:53:01.915223200-05:00[America/Bogota]","result":"SUCCESS","precondition":false,"level":2}]}]},{"number":12,"description":"When hago clic en el boton Iniciar Sesion","duration":89,"startTime":"2024-06-04T19:53:02.004246200-05:00[America/Bogota]","result":"SUCCESS","precondition":false,"level":0,"children":[{"number":13,"description":"usuario clicks on LINK BOTON INICIAR SESION HOMEPAGE","duration":82,"startTime":"2024-06-04T19:53:02.008251600-05:00[America/Bogota]","result":"SUCCESS","precondition":false,"level":1}]},{"number":14,"description":"Then deberia ver un indicador de carga mientras se verifican mis credenciales","duration":6,"startTime":"2024-06-04T19:53:02.094295900-05:00[America/Bogota]","result":"SUCCESS","precondition":false,"level":0},{"number":15,"description":"Then deberia ser redirigido a la pagina principal de la aplicacion","duration":312,"startTime":"2024-06-04T19:53:02.102298400-05:00[America/Bogota]","result":"SUCCESS","precondition":false,"level":0,"children":[{"number":16,"description":"Then El boton de perfil esta visible","duration":190,"startTime":"2024-06-04T19:53:02.220885400-05:00[America/Bogota]","result":"SUCCESS","precondition":false,"level":1}]}],"userStory":{"id":"1inicio_seccion_HU1_Sprint2","storyName":"Iniciar Sesion con Credenciales Validas.","displayName":"Iniciar Sesion con Credenciales Validas.","path":"1inicio_seccion_HU1_Sprint2","pathElements":[{"name":"1inicio_seccion_HU1_Sprint2","description":""}],"type":"feature"},"title":"Iniciar Sesion en la Aplicacion Web.","description":"","tags":[{"name":"Chrome","type":"context","displayName":"Chrome"},{"name":"Windows","type":"context","displayName":"Windows"},{"name":"Chrome, Windows","type":"context","displayName":"Chrome, Windows"},{"name":"Orden1","type":"tag","displayName":"Orden1"}],"startTime":"2024-06-04T19:52:58.266121800-05:00[America/Bogota]","duration":2754,"projectKey":"","sessionId":"bcc14fdfaa3ee0cc5334a5d07c809b49","driver":"chrome","isManualTestingUpToDate":false,"context":"chrome,windows","manual":false,"testSource":"Cucumber","actors":[{"name":"usuario","can":["browse the web"]},{"name":"administrador","can":["browse the web"]}],"order":0,"result":"SUCCESS"}